{".class": "MypyFile", "_fullname": "torch.special", "is_partial_stub_package": false, "is_stub": false, "names": {".class": "SymbolTable", "Tensor": {".class": "SymbolTableNode", "kind": "Gdef", "node": {".class": "TypeAlias", "alias_tvars": [], "column": 0, "fullname": "torch.special.Tensor", "line": 7, "no_args": true, "normalized": false, "target": "torch._tensor.Tensor"}}, "__doc__": {".class": "SymbolTableNode", "kind": "Gdef", "node": {".class": "Var", "flags": ["is_ready"], "fullname": "torch.special.__doc__", "name": "__doc__", "type": "builtins.str"}}, "__file__": {".class": "SymbolTableNode", "kind": "Gdef", "node": {".class": "Var", "flags": ["is_ready"], "fullname": "torch.special.__file__", "name": "__file__", "type": "builtins.str"}}, "__name__": {".class": "SymbolTableNode", "kind": "Gdef", "node": {".class": "Var", "flags": ["is_ready"], "fullname": "torch.special.__name__", "name": "__name__", "type": "builtins.str"}}, "__package__": {".class": "SymbolTableNode", "kind": "Gdef", "node": {".class": "Var", "flags": ["is_ready"], "fullname": "torch.special.__package__", "name": "__package__", "type": "builtins.str"}}, "_add_docstr": {".class": "SymbolTableNode", "cross_ref": "torch._C._add_docstr", "kind": "Gdef"}, "_special": {".class": "SymbolTableNode", "kind": "Gdef", "node": {".class": "Var", "flags": ["is_suppressed_import", "is_ready"], "fullname": "torch.special._special", "name": "_special", "type": {".class": "AnyType", "missing_import_name": "torch.special._special", "source_any": null, "type_of_any": 3}}}, "common_args": {".class": "SymbolTableNode", "cross_ref": "torch._torch_docs.common_args", "kind": "Gdef"}, "entr": {".class": "SymbolTableNode", "kind": "Gdef", "node": {".class": "Var", "flags": [], "fullname": "torch.special.entr", "name": "entr", "type": {".class": "AnyType", "missing_import_name": "torch.special._special", "source_any": {".class": "AnyType", "missing_import_name": "torch.special._special", "source_any": null, "type_of_any": 3}, "type_of_any": 7}}}, "erf": {".class": "SymbolTableNode", "kind": "Gdef", "node": {".class": "Var", "flags": [], "fullname": "torch.special.erf", "name": "erf", "type": {".class": "AnyType", "missing_import_name": "torch.special._special", "source_any": {".class": "AnyType", "missing_import_name": "torch.special._special", "source_any": null, "type_of_any": 3}, "type_of_any": 7}}}, "erfc": {".class": "SymbolTableNode", "kind": "Gdef", "node": {".class": "Var", "flags": [], "fullname": "torch.special.erfc", "name": "erfc", "type": {".class": "AnyType", "missing_import_name": "torch.special._special", "source_any": {".class": "AnyType", "missing_import_name": "torch.special._special", "source_any": null, "type_of_any": 3}, "type_of_any": 7}}}, "erfinv": {".class": "SymbolTableNode", "kind": "Gdef", "node": {".class": "Var", "flags": [], "fullname": "torch.special.erfinv", "name": "erfinv", "type": {".class": "AnyType", "missing_import_name": "torch.special._special", "source_any": {".class": "AnyType", "missing_import_name": "torch.special._special", "source_any": null, "type_of_any": 3}, "type_of_any": 7}}}, "exp2": {".class": "SymbolTableNode", "kind": "Gdef", "node": {".class": "Var", "flags": [], "fullname": "torch.special.exp2", "name": "exp2", "type": {".class": "AnyType", "missing_import_name": "torch.special._special", "source_any": {".class": "AnyType", "missing_import_name": "torch.special._special", "source_any": null, "type_of_any": 3}, "type_of_any": 7}}}, "expit": {".class": "SymbolTableNode", "kind": "Gdef", "node": {".class": "Var", "flags": [], "fullname": "torch.special.expit", "name": "expit", "type": {".class": "AnyType", "missing_import_name": "torch.special._special", "source_any": {".class": "AnyType", "missing_import_name": "torch.special._special", "source_any": null, "type_of_any": 3}, "type_of_any": 7}}}, "expm1": {".class": "SymbolTableNode", "kind": "Gdef", "node": {".class": "Var", "flags": [], "fullname": "torch.special.expm1", "name": "expm1", "type": {".class": "AnyType", "missing_import_name": "torch.special._special", "source_any": {".class": "AnyType", "missing_import_name": "torch.special._special", "source_any": null, "type_of_any": 3}, "type_of_any": 7}}}, "gammaln": {".class": "SymbolTableNode", "kind": "Gdef", "node": {".class": "Var", "flags": [], "fullname": "torch.special.gammaln", "name": "gammaln", "type": {".class": "AnyType", "missing_import_name": "torch.special._special", "source_any": {".class": "AnyType", "missing_import_name": "torch.special._special", "source_any": null, "type_of_any": 3}, "type_of_any": 7}}}, "i0e": {".class": "SymbolTableNode", "kind": "Gdef", "node": {".class": "Var", "flags": [], "fullname": "torch.special.i0e", "name": "i0e", "type": {".class": "AnyType", "missing_import_name": "torch.special._special", "source_any": {".class": "AnyType", "missing_import_name": "torch.special._special", "source_any": null, "type_of_any": 3}, "type_of_any": 7}}}, "logit": {".class": "SymbolTableNode", "kind": "Gdef", "node": {".class": "Var", "flags": [], "fullname": "torch.special.logit", "name": "logit", "type": {".class": "AnyType", "missing_import_name": "torch.special._special", "source_any": {".class": "AnyType", "missing_import_name": "torch.special._special", "source_any": null, "type_of_any": 3}, "type_of_any": 7}}}, "sys": {".class": "SymbolTableNode", "cross_ref": "sys", "kind": "Gdef"}, "torch": {".class": "SymbolTableNode", "cross_ref": "torch", "kind": "Gdef"}, "xlog1py": {".class": "SymbolTableNode", "kind": "Gdef", "node": {".class": "Var", "flags": [], "fullname": "torch.special.xlog1py", "name": "xlog1py", "type": {".class": "AnyType", "missing_import_name": "torch.special._special", "source_any": {".class": "AnyType", "missing_import_name": "torch.special._special", "source_any": null, "type_of_any": 3}, "type_of_any": 7}}}}, "path": "/opt/conda/lib/python3.8/site-packages/torch/special/__init__.py"}